full_adder.v
module full_adder (
    input  wire a,
    input  wire b,
    input  wire cin,
    output wire sum,
    output wire cout);

    assign sum  = a ^ b ^ cin;
    assign cout = (a & b) | (b & cin) | (a & cin);
    
endmodule

adder_subtractor_4bit.v
`include "full_adder.v"

module adder_subtractor_4bit (
    input  wire [3:0] a,
    input  wire [3:0] b,
    input  wire       sub,        // 0 = add, 1 = subtract
    output wire [3:0] sum,
    output wire       cout,
    output wire       overflow    // signed overflow flag
);

    wire [3:0] b_mod = b ^ {4{sub}};
    wire [3:0] carry;             // internal carry chain

    full_adder fa0 (.a(a[0]), .b(b_mod[0]), .cin(sub),     .sum(sum[0]), .cout(carry[0]));
    full_adder fa1 (.a(a[1]), .b(b_mod[1]), .cin(carry[0]), .sum(sum[1]), .cout(carry[1]));
    full_adder fa2 (.a(a[2]), .b(b_mod[2]), .cin(carry[1]), .sum(sum[2]), .cout(carry[2]));
    full_adder fa3 (.a(a[3]), .b(b_mod[3]), .cin(carry[2]), .sum(sum[3]), .cout(carry[3]));

    assign cout     = carry[3];
    // Signed overflow: carry into MSB differs from carry out of MSB
    assign overflow = carry[3] ^ carry[2];

endmodule

adder_subtractor_4bit_tb.v
`timescale 1ns/1ps
`include "adder_subtractor_4bit.v"

module adder_subtractor_4bit_tb;

    reg  [3:0] a, b;
    reg        sub;
    wire [3:0] sum;
    wire       cout, overflow;

    integer i;
    reg [4:0] expected;   // 5 bits to catch carry-out
    reg [4:0] a_ext, b_ext;

    adder_subtractor_4bit DUT (
        .a(a), .b(b), .sub(sub),
        .sum(sum), .cout(cout), .overflow(overflow)
    );

    initial begin
        $dumpfile("adder_subtractor_4bit.vcd");
        $dumpvars(0, adder_subtractor_4bit_tb);

        $display("---- Directed tests ----");
        a = 4'd5;  b = 4'd3;  sub = 0; #10;  // 5 + 3 = 8
        $display("ADD: %0d + %0d = %0d (cout=%b)", a, b, sum, cout);

        a = 4'd7;  b = 4'd2;  sub = 1; #10;  // 7 - 2 = 5
        $display("SUB: %0d - %0d = %0d (cout=%b)", a, b, sum, cout);

        a = 4'd3;  b = 4'd9;  sub = 1; #10;  // 3 - 9 = -6 -> wraps in 4-bit
        $display("SUB (negative): %0d - %0d = %0d (two's complement)", a, b, sum);

        a = 4'd15; b = 4'd1;  sub = 0; #10;  // overflow of unsigned range
        $display("ADD (carry out): %0d + %0d = %0d (cout=%b)", a, b, sum, cout);

        $display("---- Randomized / exhaustive-ish tests ----");
        for (i = 0; i < 50; i = i + 1) begin
            a   = $random;
            b   = $random;
            sub = $random;
            #10;
            //   ADD: zero-extend both operands and add -> bit 4 is real carry-out
            //   SUB: 4-bit wraparound subtraction; cout=1 means a>=b (no borrow)
            if (sub) begin
                expected = {1'b0, a - b};
                expected[4] = (a >= b);
            end else begin
                a_ext = {1'b0, a};
                b_ext = {1'b0, b};
                expected = a_ext + b_ext;
            end
            if ({cout, sum} !== expected)
                $display("MISMATCH: a=%0d b=%0d sub=%b -> got %0d(cout=%b) expected %0d(cout=%b)",
                          a, b, sub, sum, cout, expected[3:0], expected[4]);
        end
        $finish;
    end

endmodule

adder_subtractor_4bit.vcd
$date
	Tue Jul 07 17:29:21 2026
$end
$version
	Icarus Verilog
$end
$timescale
	1ps
$end
$scope module adder_subtractor_4bit_tb $end
$var wire 4 ! sum [3:0] $end
$var wire 1 " overflow $end
$var wire 1 # cout $end
$var reg 4 $ a [3:0] $end
$var reg 5 % a_ext [4:0] $end
$var reg 4 & b [3:0] $end
$var reg 5 ' b_ext [4:0] $end
$var reg 5 ( expected [4:0] $end
$var reg 1 ) sub $end
$var integer 32 * i [31:0] $end
$scope module DUT $end
$var wire 4 + a [3:0] $end
$var wire 4 , b [3:0] $end
$var wire 4 - b_mod [3:0] $end
$var wire 1 " overflow $end
$var wire 1 ) sub $end
$var wire 4 . sum [3:0] $end
$var wire 1 # cout $end
$var wire 4 / carry [3:0] $end
$scope module fa0 $end
$var wire 1 0 a $end
$var wire 1 1 b $end
$var wire 1 ) cin $end
$var wire 1 2 cout $end
$var wire 1 3 sum $end
$upscope $end
$scope module fa1 $end
$var wire 1 4 a $end
$var wire 1 5 b $end
$var wire 1 6 cin $end
$var wire 1 7 cout $end
$var wire 1 8 sum $end
$upscope $end
$scope module fa2 $end
$var wire 1 9 a $end
$var wire 1 : b $end
$var wire 1 ; cin $end
$var wire 1 < cout $end
$var wire 1 = sum $end
$upscope $end
$scope module fa3 $end
$var wire 1 > a $end
$var wire 1 ? b $end
$var wire 1 @ cin $end
$var wire 1 A cout $end
$var wire 1 B sum $end
$upscope $end
$upscope $end
$upscope $end
$enddefinitions $end
$comment Show the parameter values. $end
$dumpall
$end
#0
$dumpvars
1B
0A
1@
0?
0>
0=
1<
1;
0:
19
08
17
16
15
04
03
12
11
10
b111 /
b1000 .
b11 -
b11 ,
b101 +
bx *
0)
bx (
bx '
b11 &
bx %
b101 $
0#
1"
b1000 !
$end
#10000
0"
1#
b1111 /
1A
1=
0B
08
05
1:
1?
b101 !
b101 .
13
b1101 -
14
1)
b10 &
b10 ,
b111 $
b111 +
#20000
1"
0#
b111 /
0A
03
18
1B
b1010 !
b1010 .
0=
01
15
0?
b110 -
09
b1001 &
b1001 ,
b11 $
b11 +
#30000
1@
1<
08
1;
17
0"
1#
16
0=
0B
1A
b1111 /
12
11
05
0:
b0 !
b0 .
03
b1 -
19
1>
0)
b1 &
b1 ,
b1111 $
b1111 +
#40000
0=
06
02
0"
0;
1#
18
07
0B
b1100 /
1A
01
15
1:
1?
b1110 -
b11 !
b11 .
13
00
04
0>
1)
b100 $
b100 +
b0 *
#50000
0#
0"
0A
1;
0@
0B
16
17
0<
03
b11 /
12
18
b110 !
b110 .
1=
0:
0?
b10 -
10
14
09
b1101 &
b1101 ,
b11 $
b11 +
b1 *
b10011 (
#60000
1#
1A
0;
07
0"
13
1@
18
b11 !
b11 .
0=
b1101 /
1<
11
05
1:
1?
b1101 -
04
19
b10 &
b10 ,
b101 $
b101 +
b10 *
b110 (
#70000
1"
0@
b1001 /
0<
1=
b111 !
b111 .
0B
0:
b1001 -
1>
b110 &
b110 ,
b1101 $
b1101 +
b11 *
b10011 (
#80000
1@
1<
0=
0"
1;
1#
17
b1111 /
1A
08
b1 !
b1 .
0B
15
0?
b11 -
b1100 &
b1100 ,
b100 *
b10111 (
#90000
0;
07
1"
06
0=
0#
02
18
1B
b100 /
0A
05
1:
b1011 !
b1011 .
13
b101 -
00
14
0>
0)
b101 &
b101 ,
b110 $
b110 +
b101 *
b10001 (
#100000
1=
1;
17
16
b111 /
12
03
b1100 !
b1100 .
08
15
b111 -
10
04
b111 &
b111 ,
b101 $
b101 +
b110 *
b1011 (
b101 '
b110 %
#110000
06
02
0"
13
0=
1#
08
b1 !
b1 .
0B
b1110 /
1A
01
0:
b10 -
14
1>
b10 &
b10 ,
b1111 $
b1111 +
b111 *
b1100 (
b111 '
b101 %
#120000
0#
0A
0;
0"
1B
07
0@
13
08
b1101 !
b1101 .
1=
b0 /
0<
11
05
1:
b101 -
00
04
09
b101 &
b101 ,
b1000 $
b1000 +
b1000 *
b10001 (
b10 '
b1111 %
#130000
1#
1;
1A
17
0"
0B
1@
1<
16
0=
b1111 /
12
01
15
0:
b0 !
b0 .
03
b10 -
10
19
1)
b1101 &
b1101 ,
b1101 $
b1101 +
b1001 *
b1101 (
b101 '
b1000 %
#140000
0"
0@
0#
06
08
1=
0<
1B
0A
b10 /
02
1?
b1101 !
b1101 .
13
b1010 -
14
09
0>
0)
b1010 &
b1010 ,
b11 $
b11 +
b1010 *
b10000 (
#150000
0"
16
0@
12
0<
0;
1=
0B
b1 /
07
18
11
05
1:
0?
b101 -
b110 !
b110 .
03
00
04
1)
b0 $
b0 +
b1011 *
b1101 (
b1010 '
b11 %
#160000
1#
1A
06
0"
02
1@
13
0B
0;
1<
18
b1100 /
07
b11 !
b11 .
0=
01
1?
b1100 -
14
19
b11 &
b11 ,
b110 $
b110 +
b1100 *
b110 (
#170000
1;
0#
17
1"
0A
08
1@
1B
16
1<
03
b111 /
12
b1000 !
b1000 .
0=
0?
b100 -
10
09
b1011 &
b1011 ,
b11 $
b11 +
b1101 *
b10011 (
#180000
0"
0B
1;
0@
17
0<
08
1=
16
b100 !
b100 .
03
b11 /
12
11
0:
b1 -
00
b1110 &
b1110 ,
b10 $
b10 +
b1110 *
b1000 (
#190000
1#
1A
0"
18
1@
0=
b1111 /
1<
0B
15
b10 !
b10 .
03
b11 -
10
19
1>
0)
b11 &
b11 ,
b1111 $
b1111 +
b1111 *
b100 (
#200000
0;
0B
07
06
1"
18
02
0@
03
b110 !
b110 .
1=
b1000 /
0<
01
05
1:
1?
b1100 -
00
09
b1100 &
b1100 ,
b1010 $
b1010 +
b10000 *
b10010 (
b11 '
b1111 %
#210000
0"
0#
b0 /
0A
13
0=
b1011 !
b1011 .
1B
11
0:
0?
b1 -
b1 &
b1 ,
b10001 *
b10110 (
b1100 '
b1010 %
#220000
0#
0A
0"
1B
0@
0<
0;
07
06
1=
b0 /
02
18
01
15
1:
b1111 !
b1111 .
13
b110 -
04
1)
b1001 &
b1001 ,
b1000 $
b1000 +
b10010 *
b1011 (
b1 '
#230000
1"
1;
1@
17
b110 /
1<
08
1=
1B
b1100 !
b1100 .
03
14
19
0>
0)
b110 &
b110 ,
b110 $
b110 +
b10011 *
b1111 (
#240000
16
0=
12
0;
0"
07
1#
18
0B
b1101 /
1A
11
05
b10 !
b10 .
03
b101 -
04
1>
1)
b1010 &
b1010 ,
b1100 $
b1100 +
b10100 *
b1100 (
b110 '
b110 %
#250000
1;
17
0@
0"
08
0<
0#
03
1=
b1100 !
b1100 .
1B
b11 /
0A
01
15
0:
1?
b1010 -
10
09
0>
b101 &
b101 ,
b1 $
b1 +
b10101 *
b10010 (
#260000
1"
1#
1A
06
08
0B
b1010 /
02
b101 !
b101 .
13
14
1>
0)
b1010 &
b1010 ,
b1011 $
b1011 +
b10110 *
b1100 (
#270000
0"
1;
1#
17
1@
1A
16
08
1=
1<
0B
b1111 /
12
1:
b100 !
b100 .
03
b1110 -
04
19
0>
1)
b1 &
b1 ,
b101 $
b101 +
b10111 *
b10101 (
b1010 '
b1011 %
#280000
0@
0#
0<
0A
0B
16
03
b11 /
12
18
b110 !
b110 .
1=
11
0:
0?
b11 -
00
14
09
b1100 &
b1100 ,
b10 $
b10 +
b11000 *
b10100 (
#290000
1#
1A
0"
1@
13
1=
b1111 /
1<
b111 !
b111 .
0B
1:
b111 -
10
19
1>
b1000 &
b1000 ,
b1111 $
b1111 +
b11001 *
b110 (
#300000
b11 !
b11 .
0=
0:
b11 -
b1100 &
b1100 ,
b11010 *
b10111 (
#310000
0;
07
1"
0@
18
0=
b1001 /
0<
05
1?
b10 !
b10 .
03
b1001 -
04
09
0)
b1001 &
b1001 ,
b1001 $
b1001 +
b11011 *
b10011 (
#320000
1@
1<
1"
0#
1;
0A
08
b111 /
17
0=
b1000 !
b1000 .
1B
0?
b1 -
14
19
0>
b1 &
b1 ,
b111 $
b111 +
b11100 *
b10010 (
b1001 '
b1001 %
#330000
0@
0<
06
1=
0"
02
0;
0#
03
18
07
b1110 !
b1110 .
1B
b0 /
0A
01
15
b10 -
00
04
1>
b10 &
b10 ,
b1100 $
b1100 +
b11101 *
b1000 (
b1 '
b111 %
#340000
1#
1A
0"
16
1@
12
1<
1;
1=
b1111 /
17
03
08
b100 !
b100 .
0B
11
05
1:
1?
b1101 -
10
14
0>
b1101 &
b1101 ,
b111 $
b111 +
b11110 *
b1110 (
b10 '
b1100 %
#350000
06
b1110 /
02
08
0=
0B
01
15
0:
0?
b10 -
b1 !
b1 .
13
00
1>
1)
b1110 $
b1110 +
b11111 *
b10100 (
b1101 '
b111 %
#360000
1=
1B
16
b1100 !
b1100 .
03
b1111 /
12
05
1:
1?
b1100 -
10
b11 &
b11 ,
b1111 $
b1111 +
b100000 *
b10001 (
#370000
0#
0A
0"
0@
0<
1B
06
0;
13
02
08
b0 /
07
b1101 !
b1101 .
1=
0?
b100 -
00
04
09
b1011 &
b1011 ,
b1000 $
b1000 +
b100001 *
b11100 (
#380000
1;
1#
0"
17
1A
1@
1B
b1110 /
1<
08
0=
15
0:
1?
b1001 !
b1001 .
13
b1010 -
10
14
19
0)
b1010 &
b1010 ,
b1111 $
b1111 +
b100010 *
b1101 (
#390000
1=
03
b100 !
b100 .
0B
1:
b1110 -
00
0>
b1110 &
b1110 ,
b110 $
b110 +
b100011 *
b11001 (
b1010 '
b1111 %
#400000
1"
16
1;
0@
12
17
b1011 /
0<
08
1=
0B
11
05
0:
b100 !
b100 .
03
b1001 -
09
1>
1)
b110 &
b110 ,
b1010 $
b1010 +
b100100 *
b10100 (
b1110 '
b110 %
#410000
0"
0#
b11 /
0A
03
b100 !
b100 .
0B
01
0?
b0 -
10
0>
b1111 &
b1111 ,
b11 $
b11 +
b100101 *
b10100 (
#420000
1#
1A
0"
13
18
1@
0=
b1111 /
1<
b1011 !
b1011 .
1B
11
15
1?
b1011 -
19
1>
b100 &
b100 ,
b1111 $
b1111 +
b100110 *
b100 (
#430000
08
0B
06
1#
02
1A
0"
1@
0=
b1110 /
1<
01
1:
0?
b1 !
b1 .
13
b110 -
09
0)
b110 &
b110 ,
b1011 $
b1011 +
b100111 *
b11011 (
#440000
1"
0@
0<
16
1=
12
0;
03
0B
b1001 /
07
b110 !
b110 .
18
11
05
1?
b1101 -
04
b1101 &
b1101 ,
b1001 $
b1001 +
b101000 *
b10001 (
b110 '
b1011 %
#450000
0"
1;
17
1@
1#
08
1<
b1111 /
1A
0=
0B
01
15
0:
b0 !
b0 .
03
b1010 -
19
0>
1)
b101 &
b101 ,
b101 $
b101 +
b101001 *
b10110 (
b1101 '
b1001 %
#460000
0;
0#
07
0A
0"
0@
06
1=
0<
1B
b0 /
02
05
1:
0?
b1101 !
b1101 .
13
b100 -
09
1>
0)
b100 &
b100 ,
b1001 $
b1001 +
b101010 *
b10000 (
#470000
1"
1;
1#
17
b1010 /
1A
1=
0B
13
b101 !
b101 .
08
11
15
0:
1?
b1011 -
00
14
b1011 &
b1011 ,
b1010 $
b1010 +
b101011 *
b1101 (
b100 '
#480000
0;
0"
16
07
1@
12
18
0=
b1101 /
1<
05
1:
0?
b10 !
b10 .
03
b101 -
04
19
1)
b1010 &
b1010 ,
b1100 $
b1100 +
b101100 *
b10101 (
b1011 '
b1010 %
#490000
06
02
1@
1"
1;
1<
0#
08
17
0=
1B
b110 /
0A
01
15
b1001 !
b1001 .
13
b110 -
10
14
09
0>
0)
b110 &
b110 ,
b11 $
b11 +
b101101 *
b10010 (
#500000
0"
1#
b1110 /
1A
0B
b1 !
b1 .
0=
0:
1?
b1010 -
19
b1010 &
b1010 ,
b111 $
b111 +
b101110 *
b1001 (
b110 '
b11 %
#510000
0;
1"
07
0@
13
08
0=
b1000 /
0<
b1 !
b1 .
0B
11
05
b1001 -
00
04
09
1>
b1001 &
b1001 ,
b1000 $
b1000 +
b101111 *
b10001 (
b1010 '
b111 %
#520000
0"
0#
18
b0 /
0A
1=
b111 !
b111 .
0B
15
0?
b11 -
19
0>
b11 &
b11 ,
b100 $
b100 +
b110000 *
b1001 '
b1000 %
#530000
16
1=
1B
b1 /
12
01
05
1:
b1110 !
b1110 .
03
b100 -
10
09
1>
1)
b1011 &
b1011 ,
b1001 $
b1001 +
b110001 *
b111 (
b11 '
b100 %
#540000
b110010 *
b1110 (
